README.md
setup.py
zuni/__init__.py
zuni/databaseFeatures.py
zuni/llmBasedFeatures.py
zuni.egg-info/PKG-INFO
zuni.egg-info/SOURCES.txt
zuni.egg-info/dependency_links.txt
zuni.egg-info/requires.txt
zuni.egg-info/top_level.txt