Metadata-Version: 2.1
Name: zuni
Version: 0.0.5
Summary: Zillion Utility purpose Neural Interface
Home-page: UNKNOWN
Author: azhan@brace.so
License: UNKNOWN
Platform: UNKNOWN
